llama_kg/__init__.py
llama_kg/setup.py
llama_kg/index/__init__.py
llama_kg/index/base.py
llama_kg/llm_predictor/KronLLMPredictor.py
llama_kg/llm_predictor/KronLangChainLLM.py
llama_kg/llm_predictor/KronOpenAILLM.py
llama_kg/llm_predictor/__init__.py
llama_kg/llm_predictor/openai_utils.py
llama_kg/llm_predictor/utils.py
llama_kg/readers/S3ListReader.py
llama_kg/readers/S3Reader.py
llama_kg/readers/__init__.py
llama_kg-0.0.7.dist-info/LICENSE
llama_kg-0.0.7.dist-info/METADATA
llama_kg-0.0.7.dist-info/WHEEL
llama_kg-0.0.7.dist-info/top_level.txt
llama_kg-0.0.7.dist-info/RECORD
