Metadata-Version: 2.1
Name: llama-kg
Version: 0.0.7
Summary: Utilities for indexing a corpus with llama-index
License-File: LICENSE
